remis/__init__.py
remis/auth_pb2.py
remis/auth_pb2_grpc.py
remis/health_facility_pb2.py
remis/health_facility_pb2_grpc.py
remis/service_pb2.py
remis/service_pb2_grpc.py
remis/specialization_pb2.py
remis/specialization_pb2_grpc.py
remis/user_pb2.py
remis/user_pb2_grpc.py
remisprotolib-1.0.1.dist-info/METADATA
remisprotolib-1.0.1.dist-info/WHEEL
remisprotolib-1.0.1.dist-info/top_level.txt
remisprotolib-1.0.1.dist-info/RECORD
